[
  {
    "name": "zbroja skórzana",
    "space_taken": "15",
    "effect_value": "5",
    "cost_type": "",
    "uses_durability": "4",
    "cost_silver": ""
  },
  {
    "name": "zbroja półpłytowa",
    "space_taken": "30",
    "effect_value": "5",
    "cost_type": "Życie",
    "uses_durability": "6",
    "cost_silver": "2"
  },
  {
    "name": "zbroja płytowa",
    "space_taken": "50",
    "effect_value": "5",
    "cost_type": "Maksymalna ilość zakupień",
    "uses_durability": "8",
    "cost_silver": "4"
  },
  {
    "name": "zbroja płytowa (stalowa)",
    "space_taken": "X",
    "effect_value": "5",
    "cost_type": "Ilość redukowanych obrażeń",
    "uses_durability": "8",
    "cost_silver": "6"
  }
]
